dash_leaflet_basemaps/__init__.py
dash_leaflet_basemaps/basemaps.py
dash_leaflet_basemaps/py.typed
dash_leaflet_basemaps-0.1.2.dist-info/METADATA
dash_leaflet_basemaps-0.1.2.dist-info/WHEEL
dash_leaflet_basemaps-0.1.2.dist-info/licenses/AUTHORS.rst
dash_leaflet_basemaps-0.1.2.dist-info/licenses/LICENSE
dash_leaflet_basemaps-0.1.2.dist-info/RECORD
